{"title":"엘르 코리아 ─ 뷰티","url":"https://www.elle.co.kr/beauty","favicon":"https://www.elle.co.kr/favicon.ico","elements":[{"title":"이래도 단발 안 해? 단발 뽐뿌를 부르는 스타들","contents":"요즘 미모에 물오른 스타들의 공통점은 바로 단발머리!","link":"https://www.elle.co.kr/article/68176","retrieved":1658960094082,"image":"https://image.jtbcplus.kr/data/contents/jam_photo/202207/21/836a3fcc-e94a-4bab-b0c9-31f6b2b7825d.jpg"},{"title":"떡볶이, 피자 챙겨 먹어도 살 잘만 빠진다는 김신영의 다이어트 레시피 4 #스타다이어트","contents":"","link":"https://www.elle.co.kr/article/68151","retrieved":1658906112363,"image":"https://image.jtbcplus.kr/data/contents/jam_photo/202207/21/45eed01b-c603-41db-9ae8-20b3e6572c2b.jpg"},{"title":"내 일상에 녹아든, 나의 배럴핏","contents":"뮤즈 이미주가 전하는 스타일리시한 애슬레저 룩","link":"https://www.elle.co.kr/article/68069","retrieved":1658893756032,"image":"https://image.jtbcplus.kr/data/contents/jam_photo/202207/19/4c159af8-7454-4c9d-96a5-090ee85759ee.jpg"},{"title":"여름 파운데이션 하나 하셔야죠?","contents":"모든 게 완벽한 여름 파운데이션 7.","link":"https://www.elle.co.kr/article/68092","retrieved":1658720813459,"image":"https://image.jtbcplus.kr/data/contents/jam_photo/202207/19/9125e3cc-9bce-420a-b238-533f7cc673ca.jpg"},{"title":"여름에 머리 묶는 법? 기장별 묶음 머리 TIP","contents":"눈치 없이 달라붙는 머리카락으로부터 해방되는 방법! 스타들의 묶음 헤어 스타일링을 확인해 보...","link":"https://www.elle.co.kr/article/68085","retrieved":1658607377254,"image":"https://image.jtbcplus.kr/data/contents/jam_photo/202207/18/a9beeaac-60f5-436f-91b3-884ec3d10dcc.jpg"},{"title":"폭염에 뒤집어진 피부의 진정 법칙_선배's 어드바이스 #126","contents":"본격 휴가철, 잠시 방심한 사이 깜짝 놀란 피부 진정 A to Z","link":"https://www.elle.co.kr/article/68078","retrieved":1658406635643,"image":"https://image.jtbcplus.kr/data/contents/jam_photo/202207/18/2e54a448-5cff-4d96-8b28-28855ada5d23.jpg"},{"title":"갱년기 준비하기","contents":"갱년기 증후군은 빠르면 40대 초반부터 찾아온다. 지금 당장 준비가 필요하다.","link":"https://www.elle.co.kr/article/68041","retrieved":1658366135164,"image":"https://image.jtbcplus.kr/data/contents/jam_photo/202207/16/56a5d2c7-3937-4523-895b-130eae90bfe0.jpg"},{"title":"날씬한 사람들의 습관? 따뜻한 차!","contents":"연예인들의 다이어트 법에도 종종 등장하는 이것!","link":"https://www.elle.co.kr/article/68029","retrieved":1658203006598,"image":"https://image.jtbcplus.kr/data/contents/jam_photo/202207/15/04814920-8994-4ff2-a62a-2bcbf85de7e6.jpg"}]}