{"title":"엘르 코리아 ─ 컬쳐","url":"https://www.elle.co.kr/culture","favicon":"https://www.elle.co.kr/favicon.ico","elements":[{"title":"\"다 틀려 먹었어요\": '환승연애2' 찐 과몰입러 뱀뱀 어록 모음.zip (feat. 해은X현규)","contents":"","link":"https://www.elle.co.kr/article/71244","retrieved":1665069883924,"image":"https://image.jtbcplus.kr/data/contents/jam_photo/202209/30/25d902f5-a95b-4459-8639-bb20f94e1709.jpg"},{"title":"반려동물을 소장하는 또 다른 방법, 반려동물 초상화가 ‘반하라구’","contents":"민화로 만나는 나의 작고 소중한 가족","link":"https://www.elle.co.kr/article/71213","retrieved":1665069883930,"image":"https://image.jtbcplus.kr/data/contents/jam_photo/202209/30/8c4fb7cd-aeed-4b33-a27d-812a3454df96.jpg"},{"title":"꿈꾸는 여자들을 위한 신작 영화 3","contents":"마돈나와 양자경의 멀티버스, 넥스트 셀린 시아마. 이중 눈길 가는 키워드가 있다면?","link":"https://www.elle.co.kr/article/71155","retrieved":1665069883931,"image":"https://image.jtbcplus.kr/data/contents/jam_photo/202209/29/80df886f-7972-4ad8-b5bc-b3d9e2fedbb9.jpg"},{"title":"김고은-남지현-박지후의 '작은 아씨들', 동명 소설과 닮은 점이 있다고? #요즘드라마","contents":"동 시간대 시청률 1위 달성!","link":"https://www.elle.co.kr/article/71043","retrieved":1665069883933,"image":"https://image.jtbcplus.kr/data/contents/jam_photo/202209/26/1abf1e72-0d59-4e14-ac8d-9304c8cc4236.jpg"},{"title":"스포츠는 살아 있다","contents":"관건은 얼마나 쉽고 빠른지 그리고 재미있는지다.","link":"https://www.elle.co.kr/article/70263","retrieved":1665069883935,"image":"https://image.jtbcplus.kr/data/contents/jam_photo/202209/23/9f9f1660-5d6b-4d68-b7b8-eefe4bb736eb.jpg"},{"title":"솔직함을 노래하는 정진형(JEY) #2주의뮤지션","contents":"투명하게 그리고 덤덤하게. EP <algorithm>으로 출발하는 JEY의 새로운 도약.                                    </algorithm>","link":"https://www.elle.co.kr/article/70943","retrieved":1665069883936,"image":"https://image.jtbcplus.kr/data/contents/jam_photo/202209/23/7bd91222-297f-4b47-81fb-c18c79b9f715.jpg"},{"title":"배틀 레전드 찍고도 '스맨파' 첫 탈락 크루된 프라임킹즈, 눈물의 활약 모음 (feat. 악플 멈춰!)","contents":"","link":"https://www.elle.co.kr/article/70895","retrieved":1665069883939,"image":"https://image.jtbcplus.kr/data/contents/jam_photo/202209/21/314162d3-6b18-453f-a11f-1152cfc95681.jpg"},{"title":"초호화판 '디기디기딕 갱갱갱' 대잔치! '스맨파' 메가 크루 미션 영상 7 모음.zip","contents":"","link":"https://www.elle.co.kr/article/70883","retrieved":1665069883945,"image":"https://image.jtbcplus.kr/data/contents/jam_photo/202209/21/6f0a87b5-0c79-4ace-b838-43d1a7ed06fb.jpg"}]}